claim169/__init__.py
claim169/__init__.pyi
claim169/claim169.cpython-311-darwin.so
claim169-0.1.0a3.dist-info/METADATA
claim169-0.1.0a3.dist-info/WHEEL
claim169-0.1.0a3.dist-info/RECORD
