Metadata-Version: 2.4
Name: claim169
Version: 0.1.0a3
Classifier: Development Status :: 4 - Beta
Classifier: Intended Audience :: Developers
Classifier: License :: OSI Approved :: MIT License
Classifier: Programming Language :: Rust
Classifier: Programming Language :: Python :: 3
Classifier: Programming Language :: Python :: 3.8
Classifier: Programming Language :: Python :: 3.9
Classifier: Programming Language :: Python :: 3.10
Classifier: Programming Language :: Python :: 3.11
Classifier: Programming Language :: Python :: 3.12
Classifier: Topic :: Security :: Cryptography
Summary: MOSIP Claim 169 QR Code decoder library
Keywords: mosip,claim169,qr-code,identity,cbor,cose
License: MIT
Requires-Python: >=3.8
Project-URL: Repository, https://github.com/jeremi/claim-169
